hbdjinvoicing/__init__.py
hbdjinvoicing/admin.py
hbdjinvoicing/apps.py
hbdjinvoicing/conftest.py
hbdjinvoicing/models.py
hbdjinvoicing/migrations/0001_initial.py
hbdjinvoicing/migrations/0002_remove_invoice_customer_delete_customer.py
hbdjinvoicing/migrations/0003_alter_invoice_country_alter_organisation_country.py
hbdjinvoicing/migrations/0004_alter_invoice_street_alter_organisation_street.py
hbdjinvoicing/migrations/0005_invoice_customer_vat_id_alter_organisation_vat_id.py
hbdjinvoicing/migrations/__init__.py
hbdjinvoicing/static/hbdjinvoicing/invoice.css
hbdjinvoicing/static/hbdjinvoicing/sourcesanspro-bold.otf
hbdjinvoicing/static/hbdjinvoicing/sourcesanspro-regular.otf
hbdjinvoicing/templates/hbdjinvoicing/pdf.html
hbdjinvoicing/tests/__init__.py
hbdjinvoicing/tests/test_invoice.py
hbdjinvoicing-0.4.1.dist-info/licenses/LICENSE
hbdjinvoicing-0.4.1.dist-info/METADATA
hbdjinvoicing-0.4.1.dist-info/WHEEL
hbdjinvoicing-0.4.1.dist-info/top_level.txt
hbdjinvoicing-0.4.1.dist-info/RECORD
