Metadata-Version: 2.4
Name: hbdjinvoicing
Version: 0.4.1
Author-email: Hashbang <contact@hashbang.coop>
License: This License grants rights to study, execute, modify and redistribute the
License-File: LICENSE
Requires-Dist: django
Requires-Dist: psycopg2-binary
Requires-Dist: django-weasyprint
Requires-Dist: django-countries
Requires-Dist: django-localflavor
Provides-Extra: dev
Requires-Dist: pytest; extra == "dev"
Requires-Dist: django-query-counter; extra == "dev"
Requires-Dist: pytest-ruff; extra == "dev"
Requires-Dist: pytest-django; extra == "dev"
Requires-Dist: pytest-cov; extra == "dev"
Requires-Dist: diff-cover; extra == "dev"
Requires-Dist: pytest-xdist; extra == "dev"
Requires-Dist: ruff; extra == "dev"
Requires-Dist: pytest-factoryboy; extra == "dev"
Requires-Dist: pip-tools; extra == "dev"
Dynamic: license-file
